[
    {
        "name": "301강의실"
    },
    {
        "name": "302강의실"
    },
    {
        "name": "303강의실"
    },
    {
        "name": "LINC+농축산물위생및품질관리실"
    },
    {
        "name": "농약학 및 독성화학실험실"
    },
    {
        "name": "농약학 및 독성화학연구실"
    },
    {
        "name": "미생물학 및 생명공학실험실"
    },
    {
        "name": "생명자원과학관공동실험실"
    },
    {
        "name": "시료분석실"
    },
    {
        "name": "실무역량강화실"
    }, {
        "name": "토양학 및 환경화학실험실"
    },
    {
        "name": "환경자원분석센터"
    }
]
